clubcpg/CalculateBinCoverage.py
clubcpg/ClusterReads.py
clubcpg/ConnectToCpGNet.py
clubcpg/Imputation.py
clubcpg/OutputComparisonResults.py
clubcpg/ParseBam.py
clubcpg/__init__.py
clubcpg/tests/__init__.py
clubcpg/tests/test_Module.py
clubcpg_bin/__init__.py
clubcpg_bin/clubcpg_cluster.py
clubcpg_bin/clubcpg_coverage.py
clubcpg_bin/clubcpg_impute_cluster.py
clubcpg_bin/clubcpg_impute_coverage.py
clubcpg_bin/clubcpg_impute_train.py
clubcpg_prelim/PReLIM.py
clubcpg_prelim/__init__.py
clubcpg_prelim/util/CpG_Bin.py
clubcpg-0.3.0.dist-info/LICENSE
clubcpg-0.3.0.dist-info/METADATA
clubcpg-0.3.0.dist-info/WHEEL
clubcpg-0.3.0.dist-info/entry_points.txt
clubcpg-0.3.0.dist-info/RECORD
