Metadata-Version: 2.1
Name: clubcpg
Version: 0.3.0
Summary: CluBCpG is a software package built to analyze whole genome bisulfite sequencing (WGBS) data.
License: MIT
Author: Anthony Scott, PhD
Author-email: anthony@canthonyscott.com
Requires-Python: >=3.9,<3.11
Classifier: Intended Audience :: Science/Research
Classifier: License :: OSI Approved :: MIT License
Classifier: Natural Language :: English
Classifier: Operating System :: POSIX
Classifier: Operating System :: POSIX :: Linux
Classifier: Programming Language :: Python :: 3
Classifier: Programming Language :: Python :: 3.9
Classifier: Programming Language :: Python :: 3.10
Classifier: Topic :: Scientific/Engineering :: Bio-Informatics
Requires-Dist: fastcluster (>=1.2.6,<2.0.0)
Requires-Dist: joblib (>=1.3.1,<2.0.0)
Requires-Dist: numpy (>=1.25.0,<2.0.0)
Requires-Dist: pandas (>=2.0.3,<3.0.0)
Requires-Dist: pebble (>=5.0.3,<6.0.0)
Requires-Dist: pysam (>=0.21.0,<0.22.0)
Requires-Dist: scikit-learn (>=1.3.0,<2.0.0)
Requires-Dist: scipy (>=1.11.1,<2.0.0)
Requires-Dist: tqdm (>=4.65.0,<5.0.0)
